sdk/__init__.py
sdk/endpoints.py
sdk/sdk.py
lotronexyz12-0.1.0.dist-info/METADATA
lotronexyz12-0.1.0.dist-info/WHEEL
lotronexyz12-0.1.0.dist-info/top_level.txt
lotronexyz12-0.1.0.dist-info/RECORD
